trex_imager_readfile/__init__.py
trex_imager_readfile/blueline.py
trex_imager_readfile/nir.py
trex_imager_readfile/rgb.py
trex_imager_readfile/spectrograph.py
trex_imager_readfile-1.6.6.dist-info/METADATA
trex_imager_readfile-1.6.6.dist-info/WHEEL
trex_imager_readfile-1.6.6.dist-info/RECORD
