Metadata-Version: 2.1
Name: trex-imager-readfile
Version: 1.6.6
Summary: Read functions for TREx ASI raw image files
Home-page: https://github.com/ucalgary-aurora/trex-imager-readfile
License: MIT
Author: Darren Chaddock
Author-email: dchaddoc@ucalgary.ca
Requires-Python: >=3.8.1,<4.0.0
Classifier: License :: OSI Approved :: MIT License
Classifier: Programming Language :: Python :: 3
Classifier: Programming Language :: Python :: 3.9
Classifier: Programming Language :: Python :: 3.10
Classifier: Programming Language :: Python :: 3.11
Classifier: Programming Language :: Python :: 3.12
Requires-Dist: h5py (>=3.1.0,<4.0.0)
Requires-Dist: numpy (>=1.21.0,<2.0.0)
Requires-Dist: opencv-python (>=4.4.0,<5.0.0)
Project-URL: Repository, https://github.com/ucalgary-aurora/trex-imager-readfile
